ai6/__init__.py
ai6/gradient.py
ai6/hillclimbing.py
ai6/solution.py
ai6-1.2.1.dist-info/LICENSE.txt
ai6-1.2.1.dist-info/METADATA
ai6-1.2.1.dist-info/WHEEL
ai6-1.2.1.dist-info/top_level.txt
ai6-1.2.1.dist-info/RECORD
